traceroot/__init__.py
traceroot/config.py
traceroot/constants.py
traceroot/credentials.py
traceroot/logger.py
traceroot/py.typed
traceroot/tracer.py
traceroot/integrations/__init__.py
traceroot/integrations/fastapi.py
traceroot/utils/__init__.py
traceroot/utils/config.py
traceroot/utils/io.py
traceroot-0.0.7.dist-info/licenses/LICENSE
traceroot-0.0.7.dist-info/METADATA
traceroot-0.0.7.dist-info/WHEEL
traceroot-0.0.7.dist-info/top_level.txt
traceroot-0.0.7.dist-info/RECORD
