Metadata-Version: 2.4
Name: traceroot
Version: 0.0.7
Summary: The SDK that revolutionizes debugging and tracing.
Author: TraceRoot Team
License: Apache-2.0
Project-URL: Homepage, https://traceroot.ai/
Project-URL: Documentation, https://docs.traceroot.ai
Project-URL: Repository, https://github.com/traceroot-ai/traceroot-sdk
Project-URL: Bug Reports, https://github.com/traceroot-ai/traceroot-sdk/issues
Keywords: artificial-intelligence,agent-systems,opentelemetry,tracing,logging,debugging
Classifier: Development Status :: 3 - Alpha
Classifier: Intended Audience :: Developers
Classifier: License :: OSI Approved :: Apache Software License
Classifier: Programming Language :: Python :: 3
Classifier: Programming Language :: Python :: 3.8
Classifier: Programming Language :: Python :: 3.9
Classifier: Programming Language :: Python :: 3.10
Classifier: Programming Language :: Python :: 3.11
Classifier: Programming Language :: Python :: 3.12
Classifier: Topic :: Software Development :: Libraries :: Python Modules
Classifier: Topic :: System :: Logging
Classifier: Topic :: System :: Monitoring
Requires-Python: >=3.10
License-File: LICENSE
Requires-Dist: opentelemetry-api==1.34.1
Requires-Dist: opentelemetry-sdk==1.34.1
Requires-Dist: opentelemetry-exporter-otlp==1.34.1
Requires-Dist: opentelemetry-exporter-otlp-proto-common==1.34.1
Requires-Dist: opentelemetry-exporter-otlp-proto-grpc==1.34.1
Requires-Dist: opentelemetry-exporter-otlp-proto-http==1.34.1
Requires-Dist: opentelemetry-instrumentation==0.55b1
Requires-Dist: opentelemetry-instrumentation-asgi==0.55b1
Requires-Dist: opentelemetry-instrumentation-fastapi==0.55b1
Requires-Dist: opentelemetry-proto==1.34.1
Requires-Dist: opentelemetry-sdk-extension-aws==2.1.0
Requires-Dist: opentelemetry-propagator-aws-xray==1.0.2
Requires-Dist: opentelemetry-semantic-conventions==0.55b1
Requires-Dist: opentelemetry-util-http==0.55b1
Requires-Dist: watchtower==3.4.0
Requires-Dist: pandas>=1.5.0
Requires-Dist: PyYAML==6.0.2
Provides-Extra: dev
Requires-Dist: pytest==8.4.1; extra == "dev"
Requires-Dist: pytest-asyncio==1.1.0; extra == "dev"
Requires-Dist: black==25.1.0; extra == "dev"
Requires-Dist: pre-commit==4.2.0; extra == "dev"
Requires-Dist: flake8==7.3.0; extra == "dev"
Requires-Dist: mypy==1.17.0; extra == "dev"
Provides-Extra: fastapi
Requires-Dist: fastapi==0.115.12; extra == "fastapi"
Requires-Dist: uvicorn==0.34.3; extra == "fastapi"
Requires-Dist: httpx==0.27.0; extra == "fastapi"
Requires-Dist: opentelemetry-instrumentation-fastapi==0.55b1; extra == "fastapi"
Provides-Extra: all
Requires-Dist: opentelemetry-api==1.34.1; extra == "all"
Requires-Dist: opentelemetry-sdk==1.34.1; extra == "all"
Requires-Dist: opentelemetry-exporter-otlp==1.34.1; extra == "all"
Requires-Dist: opentelemetry-exporter-otlp-proto-common==1.34.1; extra == "all"
Requires-Dist: opentelemetry-exporter-otlp-proto-grpc==1.34.1; extra == "all"
Requires-Dist: opentelemetry-exporter-otlp-proto-http==1.34.1; extra == "all"
Requires-Dist: opentelemetry-instrumentation==0.55b1; extra == "all"
Requires-Dist: opentelemetry-instrumentation-asgi==0.55b1; extra == "all"
Requires-Dist: opentelemetry-instrumentation-fastapi==0.55b1; extra == "all"
Requires-Dist: opentelemetry-proto==1.34.1; extra == "all"
Requires-Dist: opentelemetry-sdk-extension-aws==2.1.0; extra == "all"
Requires-Dist: opentelemetry-propagator-aws-xray==1.0.2; extra == "all"
Requires-Dist: opentelemetry-semantic-conventions==0.55b1; extra == "all"
Requires-Dist: opentelemetry-util-http==0.55b1; extra == "all"
Requires-Dist: watchtower==3.4.0; extra == "all"
Requires-Dist: pandas>=1.5.0; extra == "all"
Requires-Dist: PyYAML==6.0.2; extra == "all"
Requires-Dist: pytest==8.4.1; extra == "all"
Requires-Dist: pytest-asyncio==1.1.0; extra == "all"
Requires-Dist: black==25.1.0; extra == "all"
Requires-Dist: flake8==7.3.0; extra == "all"
Requires-Dist: mypy==1.17.0; extra == "all"
Requires-Dist: fastapi==0.115.12; extra == "all"
Requires-Dist: uvicorn==0.34.3; extra == "all"
Requires-Dist: pre-commit==4.2.0; extra == "all"
Requires-Dist: pytest==8.4.1; extra == "all"
Requires-Dist: httpx==0.27.0; extra == "all"
Requires-Dist: opentelemetry-instrumentation-fastapi==0.55b1; extra == "all"
Dynamic: license-file
